test_session/__init__.py
test_session/print_colour.py
test_session/report_generator.py
test_session/session.py
test_session/session_timer.py
test_session/start.py
test_session/test_session_recorder.py
test_session/templates/report-template.html
test_session-0.1.dist-info/DESCRIPTION.rst
test_session-0.1.dist-info/METADATA
test_session-0.1.dist-info/RECORD
test_session-0.1.dist-info/WHEEL
test_session-0.1.dist-info/entry_points.txt
test_session-0.1.dist-info/metadata.json
test_session-0.1.dist-info/top_level.txt
